llama_index/tools/code_interpreter/__init__.py
llama_index/tools/code_interpreter/base.py
llama_index_tools_code_interpreter-0.4.1.dist-info/METADATA
llama_index_tools_code_interpreter-0.4.1.dist-info/WHEEL
llama_index_tools_code_interpreter-0.4.1.dist-info/licenses/LICENSE
llama_index_tools_code_interpreter-0.4.1.dist-info/RECORD
